sd_format/__init__.py
sd_format/service_data_conversion.py
sd_format/syntax_of_sd_format.py
sd_format-3.1.9.dist-info/LICENSE
sd_format-3.1.9.dist-info/METADATA
sd_format-3.1.9.dist-info/WHEEL
sd_format-3.1.9.dist-info/top_level.txt
sd_format-3.1.9.dist-info/RECORD
