Metadata-Version: 2.1
Name: sd-format
Version: 3.1.9
Summary: Library for working with the .sd format designed to store configuration and service data
Home-page: https://github.com/aleks-daliton/sd
Author: DALITON
Author-email: products_support@daliton.org
License: UNKNOWN
Platform: UNKNOWN
Classifier: Programming Language :: Python :: 3.8
Classifier: License :: OSI Approved :: MIT License
Classifier: Operating System :: OS Independent
Requires-Python: >=3.6
